pumpkin_py/__init__.py
pumpkin_py/builder/__init__.py
pumpkin_py/builder/annotation_builder.py
pumpkin_py/builder/graph_builder.py
pumpkin_py/config/__init__.py
pumpkin_py/config/config.py
pumpkin_py/config/example-config.yaml
pumpkin_py/graph/__init__.py
pumpkin_py/graph/graph.py
pumpkin_py/graph/ic_graph.py
pumpkin_py/models/__init__.py
pumpkin_py/models/config.py
pumpkin_py/models/dataset.py
pumpkin_py/models/methods.py
pumpkin_py/models/namespace.py
pumpkin_py/models/result.py
pumpkin_py/sim/__init__.py
pumpkin_py/sim/graph_semsim.py
pumpkin_py/sim/ic_semsim.py
pumpkin_py/sim/matrix.py
pumpkin_py/sim/metric.py
pumpkin_py/sim/search.py
pumpkin_py/sim/semantic_dist.py
pumpkin_py/store/__init__.py
pumpkin_py/store/annotation_store.py
pumpkin_py/store/ic_store.py
pumpkin_py/utils/__init__.py
pumpkin_py/utils/ic_utils.py
pumpkin_py/utils/math_utils.py
pumpkin_py/utils/ranker.py
pumpkin_py-0.0.2.dist-info/WHEEL
pumpkin_py-0.0.2.dist-info/METADATA
pumpkin_py-0.0.2.dist-info/RECORD
