Metadata-Version: 2.1
Name: pumpkin-py
Version: 0.0.2
Summary: Fast semantic search and comparison
License: BSD-3-Clause
Requires-Python: >=3.8,<=3.9
Classifier: Development Status :: 4 - Beta
Classifier: License :: OSI Approved :: BSD License
Classifier: Operating System :: POSIX :: Linux
Classifier: Programming Language :: Python
Classifier: Programming Language :: Python :: 3
Classifier: Programming Language :: Python :: 3 :: Only
Classifier: Programming Language :: Python :: 3.8
Classifier: Programming Language :: Python :: 3.9
Requires-Dist: bidict (>=0.21.2,<0.22.0)
Requires-Dist: numpy (>=1.19.0,<2.0.0)
Requires-Dist: pyroaring (>=0.3.2,<0.4.0)
Requires-Dist: rdflib (>=5.0.0,<6.0.0)
